shopyo_appadmin/__init__.py
shopyo_appadmin/admin.py
shopyo_appadmin/info.json
shopyo_appadmin/models.py
shopyo_appadmin/view.py
shopyo_appadmin/templates/shopyo_appadmin/add.html
shopyo_appadmin/templates/shopyo_appadmin/edit.html
shopyo_appadmin/templates/shopyo_appadmin/index.html
shopyo_appadmin/templates/shopyo_appadmin/roles.html
shopyo_appadmin/templates/shopyo_appadmin/blocks/sidebar.html
shopyo_appadmin-1.4.0.dist-info/METADATA
shopyo_appadmin-1.4.0.dist-info/WHEEL
shopyo_appadmin-1.4.0.dist-info/top_level.txt
shopyo_appadmin-1.4.0.dist-info/RECORD
